{"data": [{"news_url": "https://www.forbes.com/sites/greatspeculations/2019/05/06/what-effect-could-randgold-merger-and-nevada-jv-have-on-barrick-golds-q1-2019-results/", "image_url": "https://cdn.snapi.dev/images/v1/n/a/native-gold-2.jpg", "title": "What Effect Could Randgold Merger And Nevada JV Have On Barrick Gold's Q1 2019 Results?", "text": "Barrick Gold Corp is set to release its Q1 2019 results on May 08, 2019, followed by a conference call with analysts. Though the company\u2019s total revenue has been rising sequentially in the last three quarters of 2018, on a y-o-y basis revenue declined in all the quarters of 2018.", "source_name": "Forbes", "date": "Mon, 06 May 2019 16:52:00 -0400", "topics": ["earnings", "manda"], "sentiment": "Neutral", "type": "Article", "tickers": ["GOLD"]}, {"news_url": "https://www.zacks.com/stock/news/409611/barrick-gold-to-post-q1-earnings-whats-in-the-cards", "image_url": "https://cdn.snapi.dev/images/v1/r/t/gold16.jpg", "title": "Barrick (GOLD) to Post Q1 Earnings: What's in the Cards?", "text": "Our proven model shows that Barrick (GOLD) is likely to beat estimates in Q1.", "source_name": "Zacks Investment Research", "date": "Mon, 06 May 2019 11:46:00 -0400", "topics": ["earnings"], "sentiment": "Neutral", "type": "Article", "tickers": ["GOLD"]}]}